odoo/addons/__init__.py
odoo/addons/account_accountant/__init__.py
odoo/addons/account_accountant/__manifest__.py
odoo/addons/account_accountant/data/account_accountant_data.xml
odoo/addons/account_accountant/data/account_accountant_demo.xml
odoo/addons/account_accountant/data/account_accountant_tour.xml
odoo/addons/account_accountant/i18n/ar.po
odoo/addons/account_accountant/i18n/bg.po
odoo/addons/account_accountant/i18n/bs.po
odoo/addons/account_accountant/i18n/ca.po
odoo/addons/account_accountant/i18n/cs.po
odoo/addons/account_accountant/i18n/da.po
odoo/addons/account_accountant/i18n/de.po
odoo/addons/account_accountant/i18n/el.po
odoo/addons/account_accountant/i18n/es.po
odoo/addons/account_accountant/i18n/es_PE.po
odoo/addons/account_accountant/i18n/et.po
odoo/addons/account_accountant/i18n/fa.po
odoo/addons/account_accountant/i18n/fi.po
odoo/addons/account_accountant/i18n/fr.po
odoo/addons/account_accountant/i18n/he.po
odoo/addons/account_accountant/i18n/hr.po
odoo/addons/account_accountant/i18n/hu.po
odoo/addons/account_accountant/i18n/hy.po
odoo/addons/account_accountant/i18n/id.po
odoo/addons/account_accountant/i18n/it.po
odoo/addons/account_accountant/i18n/ja.po
odoo/addons/account_accountant/i18n/kab.po
odoo/addons/account_accountant/i18n/km.po
odoo/addons/account_accountant/i18n/lo.po
odoo/addons/account_accountant/i18n/lt.po
odoo/addons/account_accountant/i18n/lv.po
odoo/addons/account_accountant/i18n/mn.po
odoo/addons/account_accountant/i18n/my.po
odoo/addons/account_accountant/i18n/nb.po
odoo/addons/account_accountant/i18n/nl.po
odoo/addons/account_accountant/i18n/pl.po
odoo/addons/account_accountant/i18n/pt.po
odoo/addons/account_accountant/i18n/pt_BR.po
odoo/addons/account_accountant/i18n/ro.po
odoo/addons/account_accountant/i18n/ru.po
odoo/addons/account_accountant/i18n/sk.po
odoo/addons/account_accountant/i18n/sl.po
odoo/addons/account_accountant/i18n/sq.po
odoo/addons/account_accountant/i18n/sr.po
odooku_odoo_account_accountant-10.0.0.dist-info/DESCRIPTION.rst
odooku_odoo_account_accountant-10.0.0.dist-info/METADATA
odooku_odoo_account_accountant-10.0.0.dist-info/RECORD
odooku_odoo_account_accountant-10.0.0.dist-info/WHEEL
odooku_odoo_account_accountant-10.0.0.dist-info/metadata.json
odooku_odoo_account_accountant-10.0.0.dist-info/top_level.txt
